pyfense/__init__.py
pyfense/enemy.py
pyfense/entities.py
pyfense/game.py
pyfense/highscore.py
pyfense/hud.py
pyfense/map.py
pyfense/mapBuilder.py
pyfense/mapbuilderhud.py
pyfense/modmenu.py
pyfense/particles.py
pyfense/pause.py
pyfense/projectile.py
pyfense/projectileParticle.py
pyfense/pyfense.py
pyfense/resources.py
pyfense/tower.py
pyfense/assets/Orbitron Light.ttf
pyfense/assets/background.png
pyfense/assets/boss31.png
pyfense/assets/boss32.png
pyfense/assets/enemy01.png
pyfense/assets/enemy02.png
pyfense/assets/enemy11.png
pyfense/assets/enemy12.png
pyfense/assets/enemy21.png
pyfense/assets/enemy22.png
pyfense/assets/enemy31.png
pyfense/assets/enemy32.png
pyfense/assets/explosion0.png
pyfense/assets/explosion1.png
pyfense/assets/explosion_pictogram.png
pyfense/assets/firerate_pictogram.png
pyfense/assets/grass.png
pyfense/assets/healthBarCap.png
pyfense/assets/logo.png
pyfense/assets/lvl1.png
pyfense/assets/lvl120.png
pyfense/assets/lvl2.png
pyfense/assets/mine.png
pyfense/assets/music.wav
pyfense/assets/nopath.png
pyfense/assets/particle.png
pyfense/assets/path.png
pyfense/assets/path120.png
pyfense/assets/projectile01.png
pyfense/assets/projectile03.png
pyfense/assets/projectile11.png
pyfense/assets/projectile12.png
pyfense/assets/projectile13.png
pyfense/assets/projectile21.png
pyfense/assets/projectile22.png
pyfense/assets/projectile23.png
pyfense/assets/projectile3.png
pyfense/assets/projectile33.png
pyfense/assets/projectile_slow.png
pyfense/assets/range1920.png
pyfense/assets/selector0.png
pyfense/assets/selector1.png
pyfense/assets/shoot.wav
pyfense/assets/tower-destroy.png
pyfense/assets/tower-nocashoverlay.png
pyfense/assets/tower-noupgrade.png
pyfense/assets/tower01.png
pyfense/assets/tower02.png
pyfense/assets/tower03.png
pyfense/assets/tower11.png
pyfense/assets/tower12.png
pyfense/assets/tower13.png
pyfense/assets/tower21.png
pyfense/assets/tower22.png
pyfense/assets/tower23.png
pyfense/assets/tower31.png
pyfense/assets/tower32.png
PyFense-0.9.5.dist-info/LICENCE.md
PyFense-0.9.5.dist-info/METADATA
PyFense-0.9.5.dist-info/WHEEL
PyFense-0.9.5.dist-info/entry_points.txt
PyFense-0.9.5.dist-info/top_level.txt
PyFense-0.9.5.dist-info/RECORD
