Metadata-Version: 2.1
Name: PyFense
Version: 0.9.5
Summary: PyFense is a tower defense game built using Python 3,         the cocos2d and pyglet frameworks. If you want to contribute in any way (art, code, balancing, bug reporting)         you can do so here: https://github.com/nimarb/pyfense/ . Thank you!
Home-page: https://github.com/nimarb/pyfense
Maintainer: nimar b
Maintainer-email: l.nimar.b@gmail.com
License: GPLv3
Keywords: pyfense tower defense td game
Platform: UNKNOWN
Classifier: Programming Language :: Python
Classifier: Topic :: Games/Entertainment
Requires-Dist: pyglet (>=1.3.0)
Requires-Dist: cocos2d (>=0.6.5)
Requires-Dist: numpy (>=1.9.2)
